pyfb_rating/__init__.py
pyfb_rating/admin.py
pyfb_rating/api.py
pyfb_rating/apps.py
pyfb_rating/forms.py
pyfb_rating/models.py
pyfb_rating/serializers.py
pyfb_rating/sql_config.py
pyfb_rating/urls.py
pyfb_rating/views.py
pyfb_rating/migrations/0001_initial.py
pyfb_rating/migrations/0002_auto_20181207_1517.py
pyfb_rating/migrations/0003_auto_20181221_0855.py
pyfb_rating/migrations/0004_auto_20181221_0922.py
pyfb_rating/migrations/0005_auto_20190520_1604.py
pyfb_rating/migrations/__init__.py
pyfb_rating/static/css/pyfb_rating.css
pyfb_rating/static/js/pyfb_rating.js
pyfb_rating/templates/pyfb_rating/callernumlist_detail.html
pyfb_rating/templates/pyfb_rating/callernumlist_form.html
pyfb_rating/templates/pyfb_rating/callernumlist_list.html
pyfb_rating/templates/pyfb_rating/customercountryrate_detail.html
pyfb_rating/templates/pyfb_rating/customercountryrate_form.html
pyfb_rating/templates/pyfb_rating/customercountryrate_list.html
pyfb_rating/templates/pyfb_rating/customercountrytyperate_detail.html
pyfb_rating/templates/pyfb_rating/customercountrytyperate_form.html
pyfb_rating/templates/pyfb_rating/customercountrytyperate_list.html
pyfb_rating/templates/pyfb_rating/customerdefaultrate_detail.html
pyfb_rating/templates/pyfb_rating/customerdefaultrate_form.html
pyfb_rating/templates/pyfb_rating/customerdefaultrate_list.html
pyfb_rating/templates/pyfb_rating/customerdestinationrate_detail.html
pyfb_rating/templates/pyfb_rating/customerdestinationrate_form.html
pyfb_rating/templates/pyfb_rating/customerdestinationrate_list.html
pyfb_rating/templates/pyfb_rating/customerprefixrate_detail.html
pyfb_rating/templates/pyfb_rating/customerprefixrate_form.html
pyfb_rating/templates/pyfb_rating/customerprefixrate_list.html
pyfb_rating/templates/pyfb_rating/customerratecard_detail.html
pyfb_rating/templates/pyfb_rating/customerratecard_form.html
pyfb_rating/templates/pyfb_rating/customerratecard_list.html
pyfb_rating/templates/pyfb_rating/customerrcallocation_detail.html
pyfb_rating-1.0.0.dist-info/AUTHORS.rst
pyfb_rating-1.0.0.dist-info/LICENSE
pyfb_rating-1.0.0.dist-info/METADATA
pyfb_rating-1.0.0.dist-info/WHEEL
pyfb_rating-1.0.0.dist-info/top_level.txt
pyfb_rating-1.0.0.dist-info/RECORD
